langgraph/checkpoint/base/__init__.py
langgraph/checkpoint/base/id.py
langgraph/checkpoint/memory/__init__.py
langgraph/checkpoint/py.typed
langgraph/checkpoint/serde/__init__.py
langgraph/checkpoint/serde/base.py
langgraph/checkpoint/serde/jsonplus.py
langgraph/checkpoint/serde/types.py
gigagraph_checkpoint-1.0.9.dist-info/LICENSE
gigagraph_checkpoint-1.0.9.dist-info/METADATA
gigagraph_checkpoint-1.0.9.dist-info/WHEEL
gigagraph_checkpoint-1.0.9.dist-info/RECORD
