Metadata-Version: 2.1
Name: gigagraph-checkpoint
Version: 1.0.9
Summary: Library with base interfaces for LangGraph checkpoint savers.
Home-page: https://github.com/ai-forever/gigagraph
License: MIT
Requires-Python: >=3.9.0,<4.0.0
Classifier: License :: OSI Approved :: MIT License
Classifier: Programming Language :: Python :: 3
Classifier: Programming Language :: Python :: 3.9
Classifier: Programming Language :: Python :: 3.10
Classifier: Programming Language :: Python :: 3.11
Classifier: Programming Language :: Python :: 3.12
Requires-Dist: gigachain-core (>=0.2.38post2,<0.4)
Project-URL: Repository, https://github.com/ai-forever/gigagraph
